olas/__init__.py
olas/estela.py
olas-0.4.0.dist-info/WHEEL
olas-0.4.0.dist-info/entry_points.txt
olas-0.4.0.dist-info/METADATA
olas-0.4.0.dist-info/RECORD
