Metadata-Version: 2.4
Name: olas
Version: 0.4.0
Summary: Library with wave tools like ESTELA
Keywords: waves,xarray,ESTELA
Author: Jorge Perez
Author-email: Jorge Perez <j.perez@metocean.co.nz>
License-Expression: MIT
Classifier: Development Status :: 4 - Beta
Classifier: Intended Audience :: Science/Research
Classifier: Programming Language :: Python :: 3
Classifier: Programming Language :: Python :: 3.9
Classifier: Programming Language :: Python :: 3.10
Classifier: Programming Language :: Python :: 3.11
Classifier: Programming Language :: Python :: 3.12
Classifier: Programming Language :: Python :: 3.13
Classifier: Programming Language :: Python :: 3.14
Requires-Dist: xarray>=2023.1.0
Requires-Dist: dask[dataframe,diagnostics,distributed]>=2023.3.1
Requires-Dist: scipy>=1.10.1
Requires-Dist: numpy>=1.24.2
Requires-Dist: matplotlib>=3.7.1
Requires-Dist: netcdf4>=1.6.3
Requires-Dist: cartopy>=0.21.1
Requires-Dist: pytest>=7.2.2 ; extra == 'dev'
Requires-Dist: ipython>=8.11.0 ; extra == 'dev'
Requires-Dist: ipdb>=0.12.3 ; extra == 'dev'
Requires-Dist: prek>=0.2 ; extra == 'dev'
Requires-Dist: mkdocs-material>=9 ; extra == 'dev'
Requires-Python: >=3.9, <3.15
Project-URL: documentation, https://jorgeperezg.github.io/olas
Project-URL: homepage, https://github.com/jorgeperezg/olas
Project-URL: repository, https://github.com/jorgeperezg/olas
Provides-Extra: dev
